[{"id":"202458500000101441","name":"제암산휴양림화장실","lat":34.707481,"lng":126.983876,"roadAddr":"전남광주통합특별시 보성군 웅치면 대산리 산113-1","jibunAddr":"전남광주통합특별시 보성군 웅치면 대산리 산113-1","openHours":"상시","maleToilets":6,"femaleToilets":6,"disabled":true,"diaperTable":false,"emergencyBell":false,"cctv":false,"managerTel":"0618505335","source":"public","category":"public"},{"id":"202458600000100596","name":"제암산등산로","lat":34.691965,"lng":126.967813,"roadAddr":"전남광주통합특별시 장흥군 장흥읍 금산신기길 124-93","jibunAddr":"전남광주통합특별시 장흥군 장흥읍 금산리 산 1-3","openHours":"상시","maleToilets":1,"femaleToilets":1,"disabled":false,"diaperTable":false,"emergencyBell":false,"cctv":false,"managerTel":"0618606054","source":"public","category":"public"},{"id":"202458600000100624","name":"장흥공설공원묘지","lat":34.699045,"lng":126.958171,"roadAddr":"전남광주통합특별시 장흥군 장흥읍 금산신기길 131","jibunAddr":"전남광주통합특별시 장흥군 장흥읍 금산리 산 28","openHours":"상시","maleToilets":4,"femaleToilets":2,"disabled":false,"diaperTable":false,"emergencyBell":false,"cctv":false,"source":"public","category":"public"}]