[{"id":"202457850000100050","name":"묘도주유소","lat":34.880857,"lng":127.709619,"roadAddr":"전남광주통합특별시 여수시 묘도1길 142 (묘도동)","openHours":"09:00~18:00","maleToilets":2,"femaleToilets":1,"disabled":true,"diaperTable":false,"emergencyBell":false,"cctv":false,"managerTel":"0616859106","source":"public","category":"public"},{"id":"202457850000100004","name":"한가득주유소","lat":34.879864,"lng":127.714273,"roadAddr":"전남광주통합특별시 여수시 이순신대로 286 (묘도동)","openHours":"06:00~23:00","maleToilets":2,"femaleToilets":1,"disabled":true,"diaperTable":false,"emergencyBell":false,"cctv":true,"managerTel":"0616867084","source":"public","category":"public"},{"id":"202457850000100005","name":"이순신대교 주유소","lat":34.879924,"lng":127.714941,"roadAddr":"전남광주통합특별시 여수시 이순신대로 272","openHours":"06:00~23:50","maleToilets":2,"femaleToilets":2,"disabled":false,"diaperTable":false,"emergencyBell":false,"cctv":true,"managerTel":"0616555151","source":"public","category":"public"},{"id":"202457850000100347","name":"묘도동 주민센터","lat":34.874685,"lng":127.709376,"roadAddr":"전남광주통합특별시 여수시 묘도1길 67 (묘도동, 묘도동주민센터)","jibunAddr":"전남광주통합특별시 여수시 묘도동 915-1","openHours":"09:00~18:00","maleToilets":5,"femaleToilets":2,"disabled":false,"diaperTable":false,"emergencyBell":false,"cctv":false,"managerTel":"0616591686","source":"public","category":"public"},{"id":"202457850000100105","name":"묘도동 주민자치센터","lat":34.874815,"lng":127.710731,"roadAddr":"전남광주통합특별시 여수시 묘도1길 60 (묘도동)","openHours":"09:00~18:00","maleToilets":3,"femaleToilets":2,"disabled":false,"diaperTable":false,"emergencyBell":false,"cctv":false,"managerTel":"0616591686","source":"public","category":"public"},{"id":"202457850000100177","name":"묘도보건진료소","lat":34.885334,"lng":127.713419,"roadAddr":"전남광주통합특별시 여수시 묘도10길 6 (묘도동, 묘도보건진료소)","openHours":"09:00~18:00","maleToilets":1,"femaleToilets":1,"disabled":false,"diaperTable":false,"emergencyBell":false,"cctv":false,"managerTel":"0616853386","source":"public","category":"public"}]