[{"id":"202453300000101257","name":"유동 공중화장실","lat":34.620857,"lng":128.243021,"roadAddr":"경상남도 통영시 욕지면 유동길106-20","openHours":"상시","maleToilets":6,"femaleToilets":3,"disabled":false,"diaperTable":false,"emergencyBell":true,"cctv":true,"managerTel":"0556500622","source":"public","category":"public"},{"id":"202453300000101258","name":"새천년공원 공중화장실","lat":34.62484,"lng":128.259867,"roadAddr":"경상남도 통영시 욕지면 동항리산95-76","openHours":"상시","maleToilets":1,"femaleToilets":1,"disabled":false,"diaperTable":false,"emergencyBell":false,"cctv":false,"managerTel":"0556505462","source":"public","category":"public"}]