[{"id":"202547610000100023","name":"세심보건진료소","lat":35.493284,"lng":127.244612,"roadAddr":"전북특별자치도 임실군 삼계면 세심길 80","jibunAddr":"전북특별자치도 임실군 삼계면 세심길 80","openHours":"정시","maleToilets":1,"femaleToilets":0,"disabled":false,"diaperTable":false,"emergencyBell":false,"cctv":false,"managerTel":"0636427763","source":"public","category":"public"},{"id":"202547610000100071","name":"학정제수지","lat":35.495515,"lng":127.224115,"roadAddr":"전북특별자치도 임실군 삼계면 학정리1053","jibunAddr":"전북특별자치도 임실군 삼계면 학정리1053","openHours":"정시","maleToilets":2,"femaleToilets":1,"disabled":false,"diaperTable":false,"emergencyBell":false,"cctv":false,"managerTel":"0636404253","source":"public","category":"public"},{"id":"202547610000100073","name":"홍곡리공원","lat":35.488929,"lng":127.263076,"roadAddr":"전북특별자치도 임실군 삼계면 홍곡리1158","jibunAddr":"전북특별자치도 임실군 삼계면 홍곡리1158","openHours":"정시","maleToilets":3,"femaleToilets":1,"disabled":false,"diaperTable":false,"emergencyBell":false,"cctv":false,"managerTel":"0636404253","source":"public","category":"public"}]