[{"id":"202547310000100142","name":"명마대","lat":35.703963,"lng":127.387262,"roadAddr":"전북특별자치도 진안군 백운면 덕현리 6(정자)","openHours":"상시","maleToilets":2,"femaleToilets":1,"disabled":false,"diaperTable":false,"emergencyBell":false,"cctv":false,"managerTel":"0634308297","source":"public","category":"public"},{"id":"202547310000100130","name":"모은정","lat":35.707968,"lng":127.392221,"roadAddr":"전북특별자치도 진안군 백운면 원운1길 29-7","openHours":"상시","maleToilets":2,"femaleToilets":1,"disabled":false,"diaperTable":false,"emergencyBell":false,"cctv":false,"managerTel":"0634308297","source":"public","category":"public"},{"id":"202547310000100141","name":"내동숲","lat":35.694474,"lng":127.389198,"roadAddr":"전북특별자치도 진안군 백운면 덕현리 275-1","openHours":"상시","maleToilets":2,"femaleToilets":1,"disabled":false,"diaperTable":false,"emergencyBell":false,"cctv":false,"managerTel":"0634308297","source":"public","category":"public"}]