[{"id":"202547310000100033","name":"능금보건진료소","lat":35.859992,"lng":127.59193,"roadAddr":"전북특별자치도 진안군 동향면 능금로 203","openHours":"정시","maleToilets":0,"femaleToilets":0,"disabled":false,"diaperTable":false,"emergencyBell":false,"cctv":false,"managerTel":"0634308971","source":"public","category":"public"},{"id":"202447410000100296","name":"교동 삼거리 이동식화장실","lat":35.902332,"lng":127.589885,"jibunAddr":"전북특별자치도 무주군 부남면  장안리","openHours":"상시","maleToilets":1,"femaleToilets":1,"disabled":false,"diaperTable":false,"emergencyBell":false,"cctv":false,"managerTel":"0633205953","source":"public","category":"public"}]