[{"id":"202436400000100476","name":"곤룡쉼터","lat":36.279193,"lng":127.488002,"roadAddr":"대전광역시 동구 곤룡로 210","jibunAddr":"대전광역시 동구 낭월동 산4-18","openHours":"상시","maleToilets":2,"femaleToilets":1,"disabled":false,"diaperTable":false,"emergencyBell":false,"cctv":false,"managerTel":"0422514584","source":"public","category":"public"},{"id":"202444300000100878","name":"은행리소공원","lat":36.271238,"lng":127.522034,"roadAddr":"충청북도 옥천군 군서면 곤룡로 572","openHours":"상시","maleToilets":2,"femaleToilets":2,"disabled":false,"diaperTable":false,"emergencyBell":true,"cctv":true,"source":"public","category":"public"},{"id":"202444300000100915","name":"은행보건진료소","lat":36.270232,"lng":127.516875,"roadAddr":"충청북도 옥천군 군서면 은행1길 25","openHours":"상시","maleToilets":0,"femaleToilets":0,"disabled":true,"diaperTable":false,"emergencyBell":false,"cctv":false,"source":"public","category":"public"},{"id":"202444300000100916","name":"군서보건지소","lat":36.279866,"lng":127.527406,"roadAddr":"충청북도 옥천군 군서면 성왕로 540","openHours":"상시","maleToilets":4,"femaleToilets":2,"disabled":true,"diaperTable":false,"emergencyBell":true,"cctv":false,"source":"public","category":"public"},{"id":"202444300000100879","name":"군서면사무소","lat":36.279866,"lng":127.527406,"roadAddr":"충청북도 옥천군 군서면 성왕로 540","openHours":"상시","maleToilets":9,"femaleToilets":3,"disabled":true,"diaperTable":false,"emergencyBell":true,"cctv":false,"source":"public","category":"public"}]