[{"id":"202453100000102070","name":"진양호주유소","lat":35.170735,"lng":128.041947,"roadAddr":"경상남도 진주시 판문오동길 36","jibunAddr":"경상남도 진주시 판문동 228-1","openHours":"정시","maleToilets":4,"femaleToilets":1,"disabled":false,"diaperTable":false,"emergencyBell":false,"cctv":false,"managerTel":"0557495233","source":"public","category":"public"},{"id":"202453100000102317","name":"상락원","lat":35.184594,"lng":128.032139,"roadAddr":"경상남도 진주시 판문오동길 115번길 62-33","jibunAddr":"경상남도 진주시 판문동 1032","openHours":"정시","maleToilets":23,"femaleToilets":12,"disabled":false,"diaperTable":false,"emergencyBell":false,"cctv":false,"managerTel":"0557495943","source":"public","category":"public"},{"id":"202453100000102240","name":"진양호공원(가족쉼터)","lat":35.17301,"lng":128.037458,"roadAddr":"경상남도 진주시 남강로 1번길 73","jibunAddr":"경상남도 진주시 판문동 465-1","openHours":"상시","maleToilets":5,"femaleToilets":5,"disabled":true,"diaperTable":true,"emergencyBell":true,"cctv":true,"managerTel":"0557495933","source":"public","category":"public"},{"id":"202453100000102239","name":"진양호공원(광장)","lat":35.176192,"lng":128.035019,"roadAddr":"경상남도 진주시 남강로 1번길 126","jibunAddr":"경상남도 진주시 판문동 산171-1","openHours":"상시","maleToilets":10,"femaleToilets":4,"disabled":true,"diaperTable":true,"emergencyBell":true,"cctv":true,"managerTel":"0557495933","source":"public","category":"public"},{"id":"202453100000102028","name":"진주국토관리사무소","lat":35.163347,"lng":128.038005,"roadAddr":"경상남도 진주시 남강로 50, 진주국토관리사무소 (평거동)","jibunAddr":"경상남도 진주시 평거동 695-90 진주국도유지건설사업소","openHours":"정시","maleToilets":2,"femaleToilets":1,"disabled":false,"diaperTable":false,"emergencyBell":false,"cctv":false,"managerTel":"0557402614","source":"public","category":"public"},{"id":"202453100000102251","name":"진양호 쉼터","lat":35.170843,"lng":128.038328,"jibunAddr":"경상남도 진주시 판문동 산 204-18","openHours":"상시","maleToilets":2,"femaleToilets":2,"disabled":false,"diaperTable":false,"emergencyBell":true,"cctv":true,"managerTel":"0557495933","source":"public","category":"public"},{"id":"202453100000102415","name":"판문동행정복지센터","lat":35.166855,"lng":128.054629,"roadAddr":"경상남도 진주시 새평거로55","jibunAddr":"경상남도 진주시 평거동 796","openHours":"정시","maleToilets":13,"femaleToilets":7,"disabled":true,"diaperTable":false,"emergencyBell":false,"cctv":false,"managerTel":"0557494504","source":"public","category":"public"},{"id":"202453100000102414","name":"서진주ic주차장","lat":35.186554,"lng":128.045546,"jibunAddr":"경상남도 진주시 판문동 68-1","openHours":"상시","maleToilets":3,"femaleToilets":3,"disabled":false,"diaperTable":false,"emergencyBell":true,"cctv":false,"managerTel":"0557494504","source":"public","category":"public"},{"id":"202453100000102416","name":"판문동 습지원 남강둔치","lat":35.15983,"lng":128.046146,"jibunAddr":"경상남도 진주시 평거동 695-93","openHours":"상시","maleToilets":4,"femaleToilets":4,"disabled":false,"diaperTable":false,"emergencyBell":true,"cctv":true,"managerTel":"0557494504","source":"public","category":"public"},{"id":"202453100000102230","name":"석갑산 등산로 화장실 2","lat":35.184337,"lng":128.055667,"jibunAddr":"경상남도 진주시 이현동 147","openHours":"상시","maleToilets":0,"femaleToilets":1,"disabled":true,"diaperTable":true,"emergencyBell":false,"cctv":false,"managerTel":"0557498778","source":"public","category":"public"},{"id":"202453100000102318","name":"진주시능력개발관(본관)","lat":35.15924,"lng":128.032108,"roadAddr":"경상남도 진주시 내동면 삼계로 430","jibunAddr":"경상남도 진주시 내동면 삼계리 663","openHours":"정시","maleToilets":20,"femaleToilets":19,"disabled":true,"diaperTable":true,"emergencyBell":false,"cctv":false,"managerTel":"0557495951","source":"public","category":"public"},{"id":"202453100000102238","name":"진양호공원(동물원)","lat":35.17661,"lng":128.036268,"roadAddr":"경상남도 진주시 남강로 1번길 130","jibunAddr":"경상남도 진주시 판문동 산171-1","openHours":"상시","maleToilets":6,"femaleToilets":3,"disabled":true,"diaperTable":true,"emergencyBell":true,"cctv":true,"managerTel":"0557495933","source":"public","category":"public"},{"id":"202453100000102237","name":"진양호공원(매점)","lat":35.173727,"lng":128.035629,"roadAddr":"경상남도 진주시 남강로 1번길 103","jibunAddr":"경상남도 진주시 판문동 산173-16","openHours":"상시","maleToilets":10,"femaleToilets":4,"disabled":true,"diaperTable":true,"emergencyBell":true,"cctv":true,"managerTel":"0557495933","source":"public","category":"public"},{"id":"202453100000101965","name":"물문화관","lat":35.162528,"lng":128.030353,"roadAddr":"경상남도 진주시 내동면 삼계로 455-46","jibunAddr":"경상남도 진주시 내동면 삼계리 683-14","openHours":"정시","maleToilets":10,"femaleToilets":7,"disabled":true,"diaperTable":true,"emergencyBell":true,"cctv":false,"managerTel":"0557601266","source":"public","category":"public"},{"id":"202453100000102168","name":"소싸움경기장","lat":35.175982,"lng":128.040639,"roadAddr":"경상남도 진주시 판문오동길 100","jibunAddr":"경상남도 진주시 판문동 146-1","openHours":"정시","maleToilets":14,"femaleToilets":8,"disabled":true,"diaperTable":true,"emergencyBell":false,"cctv":false,"managerTel":"0557498597","source":"public","category":"public"},{"id":"202453100000102002","name":"진주평거동우체국","lat":35.169241,"lng":128.052567,"roadAddr":"경상남도 진주시 진양호로125번길 15, 진주평거동우체국 (평거동)","jibunAddr":"경상남도 진주시 평거동 726-1 진주평거동우체국","openHours":"정시","maleToilets":1,"femaleToilets":1,"disabled":true,"diaperTable":false,"emergencyBell":false,"cctv":false,"managerTel":"0557474717","source":"public","category":"public"},{"id":"202453100000102076","name":"㈜홍성주유소","lat":35.183572,"lng":128.040058,"roadAddr":"경상남도 진주시 판문로 192","jibunAddr":"경상남도 진주시 판문동 517-16","openHours":"정시","maleToilets":7,"femaleToilets":3,"disabled":false,"diaperTable":false,"emergencyBell":false,"cctv":false,"managerTel":"0557495233","source":"public","category":"public"},{"id":"202453100000101966","name":"노을공원","lat":35.161238,"lng":128.030406,"roadAddr":"경상남도 진주시 내동면 삼계로 453","jibunAddr":"경상남도 진주시 내동면 삼계리 682-1","openHours":"상시","maleToilets":9,"femaleToilets":13,"disabled":true,"diaperTable":true,"emergencyBell":true,"cctv":false,"managerTel":"0557601240","source":"public","category":"public"},{"id":"202453100000102232","name":"숙호산 등산로 화장실 2","lat":35.187007,"lng":128.054019,"jibunAddr":"경상남도 진주시 이현동 산93-5","openHours":"상시","maleToilets":0,"femaleToilets":0,"disabled":true,"diaperTable":true,"emergencyBell":true,"cctv":true,"managerTel":"0557498778","source":"public","category":"public"},{"id":"202453100000102069","name":"진주개인택시2충전소","lat":35.200106,"lng":128.052148,"roadAddr":"경상남도 진주시 진주대로 1409","jibunAddr":"경상남도 진주시 이현동 686-3","openHours":"정시","maleToilets":3,"femaleToilets":1,"disabled":false,"diaperTable":false,"emergencyBell":false,"cctv":false,"managerTel":"0557495233","source":"public","category":"public"},{"id":"202453100000102079","name":"㈜성홍가스서진주충전소","lat":35.183888,"lng":128.039974,"roadAddr":"경상남도 진주시 판문로 194","jibunAddr":"경상남도 진주시 판문동 517-1","openHours":"정시","maleToilets":7,"femaleToilets":3,"disabled":false,"diaperTable":false,"emergencyBell":false,"cctv":false,"managerTel":"0557495233","source":"public","category":"public"},{"id":"202453100000102053","name":"판문현대주유소","lat":35.167649,"lng":128.042245,"roadAddr":"경상남도 진주시 진양호로 21","jibunAddr":"경상남도 진주시 판문동 306-1","openHours":"정시","maleToilets":4,"femaleToilets":2,"disabled":false,"diaperTable":false,"emergencyBell":false,"cctv":false,"managerTel":"0557495233","source":"public","category":"public"},{"id":"202453100000102248","name":"평거4지구근린공원1","lat":35.164449,"lng":128.049013,"roadAddr":"경상남도 진주시 진양호로 84번길 32","jibunAddr":"경상남도 진주시 평거동 1107","openHours":"상시","maleToilets":6,"femaleToilets":4,"disabled":true,"diaperTable":false,"emergencyBell":true,"cctv":true,"managerTel":"0557498752","source":"public","category":"public"},{"id":"202453100000102250","name":"진양호공원(전망대)","lat":35.17662,"lng":128.03258,"roadAddr":"경상남도 진주시 남강로 1번길 146","jibunAddr":"경상남도 진주시 판문동 산171-5","openHours":"상시","maleToilets":5,"femaleToilets":2,"disabled":true,"diaperTable":false,"emergencyBell":true,"cctv":false,"managerTel":"0557495933","source":"public","category":"public"},{"id":"202453100000102231","name":"숙호산 등산로 화장실 1","lat":35.191855,"lng":128.048502,"jibunAddr":"경상남도 진주시 이현동 402","openHours":"상시","maleToilets":3,"femaleToilets":3,"disabled":false,"diaperTable":false,"emergencyBell":true,"cctv":false,"managerTel":"0557498778","source":"public","category":"public"}]