[{"id":"202451900000100748","name":"매전면복합체육시설","lat":35.665361,"lng":128.854752,"jibunAddr":"경상북도 청도군 매전면 동산리286","openHours":"상시","maleToilets":1,"femaleToilets":0,"disabled":true,"diaperTable":false,"emergencyBell":false,"cctv":false,"managerTel":"0543702613","source":"public","category":"public"},{"id":"202451900000100687","name":"매전우체국","lat":35.666783,"lng":128.85525,"jibunAddr":"경상북도 청도군 매전면 동산리233-14","openHours":"09:00~18:00","maleToilets":1,"femaleToilets":0,"disabled":true,"diaperTable":false,"emergencyBell":false,"cctv":true,"managerTel":"0543725001","source":"public","category":"public"},{"id":"202451900000100691","name":"매전면사무소","lat":35.667176,"lng":128.855587,"jibunAddr":"경상북도 청도군 매전면 동산리233-1","openHours":"09:00~18:00","maleToilets":3,"femaleToilets":0,"disabled":true,"diaperTable":false,"emergencyBell":false,"cctv":false,"managerTel":"0543702613","source":"public","category":"public"},{"id":"202451900000100780","name":"매전농협주유소","lat":35.671487,"lng":128.860833,"jibunAddr":"경상북도 청도군 매전면 동산리21-2","openHours":"09:00~18:00","maleToilets":1,"femaleToilets":0,"disabled":true,"diaperTable":false,"emergencyBell":false,"cctv":false,"managerTel":"0543715675","source":"public","category":"public"},{"id":"202451900000100707","name":"매전보건지소","lat":35.666658,"lng":128.854478,"jibunAddr":"경상북도 청도군 매전면 동산리234-1","openHours":"09:00~18:00","maleToilets":3,"femaleToilets":0,"disabled":true,"diaperTable":false,"emergencyBell":false,"cctv":false,"managerTel":"0543706469","source":"public","category":"public"}]