[{"id":"202451410000100087","name":"쉬었다가세요 식당 앞 다리밑","lat":36.071497,"lng":128.658627,"jibunAddr":"대구광역시 군위군 부계면 춘산리 79-1","openHours":"상시","maleToilets":2,"femaleToilets":1,"disabled":false,"diaperTable":false,"emergencyBell":false,"cctv":false,"managerTel":"0543806742","source":"public","category":"public"},{"id":"202451410000100089","name":"동산주차장(분양부지)","lat":36.049955,"lng":128.645867,"roadAddr":"대구광역시 군위군 부계면 한티로 1943","jibunAddr":"대구광역시 군위군 부계면 동산리 1651","openHours":"상시","maleToilets":3,"femaleToilets":2,"disabled":false,"diaperTable":false,"emergencyBell":false,"cctv":false,"managerTel":"0543806742","source":"public","category":"public"},{"id":"202451410000100085","name":"동산계곡 주차장","lat":36.040913,"lng":128.668725,"roadAddr":"대구광역시 군위군 부계면 원효길 183","jibunAddr":"대구광역시 군위군 부계면 동산리 320-2","openHours":"상시","maleToilets":5,"femaleToilets":4,"disabled":false,"diaperTable":false,"emergencyBell":false,"cctv":false,"managerTel":"0543806742","source":"public","category":"public"},{"id":"202451410000100091","name":"농산물판매장","lat":36.050001,"lng":128.649106,"jibunAddr":"대구광역시 군위군 부계면 동산리 1507-1","openHours":"상시","maleToilets":2,"femaleToilets":1,"disabled":true,"diaperTable":false,"emergencyBell":false,"cctv":false,"managerTel":"0543806742","source":"public","category":"public"},{"id":"202451410000100018","name":"대율리 입구 주차장 옆","lat":36.059079,"lng":128.657384,"jibunAddr":"대구광역시 군위군 부계면 대율리 1357-1","openHours":"상시","maleToilets":4,"femaleToilets":4,"disabled":false,"diaperTable":false,"emergencyBell":false,"cctv":false,"managerTel":"0543806916","source":"public","category":"public"},{"id":"202451410000100140","name":"대율리 공중화장실","lat":36.061298,"lng":128.655294,"roadAddr":"대구광역시 군위군 부계면 한티로 2157","jibunAddr":"대구광역시 군위군 부계면 대율리 666-1","openHours":"상시","maleToilets":6,"femaleToilets":6,"disabled":false,"diaperTable":false,"emergencyBell":true,"cctv":false,"managerTel":"0543807924","source":"public","category":"public"},{"id":"202351410000100049","name":"대율리 입구 주차장","lat":36.06457,"lng":128.656426,"roadAddr":"대구광역시 군위군 부계면 한티로 2193-5","jibunAddr":"대구광역시 군위군 부계면 대율리 559","openHours":"상시","maleToilets":4,"femaleToilets":3,"disabled":false,"diaperTable":false,"emergencyBell":false,"cctv":false,"managerTel":"0543806742","source":"public","category":"public"},{"id":"202351410000100059","name":"동산계곡식당 밑 주차장","lat":36.03958,"lng":128.669765,"jibunAddr":"대구광역시 군위군 부계면 동산리 317-1","openHours":"상시","maleToilets":2,"femaleToilets":1,"disabled":false,"diaperTable":false,"emergencyBell":false,"cctv":false,"managerTel":"0543806742","source":"public","category":"public"},{"id":"202351410000100056","name":"동산계곡 입구","lat":36.046218,"lng":128.660457,"jibunAddr":"대구광역시 군위군 부계면 동산리 산59-2","openHours":"상시","maleToilets":2,"femaleToilets":1,"disabled":false,"diaperTable":false,"emergencyBell":false,"cctv":false,"managerTel":"0543806742","source":"public","category":"public"},{"id":"202351410000100052","name":"석굴암주차장","lat":36.047825,"lng":128.643112,"roadAddr":"대구광역시 군위군 부계면 한티로 1904","jibunAddr":"대구광역시 군위군 부계면 남산리 317-1","openHours":"상시","maleToilets":4,"femaleToilets":4,"disabled":true,"diaperTable":false,"emergencyBell":true,"cctv":false,"managerTel":"0543806742","source":"public","category":"public"},{"id":"202351410000100054","name":"석굴암 화장실","lat":36.048247,"lng":128.64143,"roadAddr":"대구광역시 군위군 부계면 남산4길 22","jibunAddr":"대구광역시 군위군 부계면 남산리 310-1","openHours":"상시","maleToilets":6,"femaleToilets":6,"disabled":true,"diaperTable":true,"emergencyBell":false,"cctv":false,"managerTel":"0543806742","source":"public","category":"public"},{"id":"202351410000100050","name":"대율리 소공원(갈매기아파트","lat":36.054731,"lng":128.655489,"jibunAddr":"대구광역시 군위군 부계면 대율리 1170-1","openHours":"상시","maleToilets":3,"femaleToilets":1,"disabled":false,"diaperTable":false,"emergencyBell":false,"cctv":false,"managerTel":"0543806742","source":"public","category":"public"},{"id":"202451410000100082","name":"동산계곡 저수지 상류","lat":36.036793,"lng":128.671398,"jibunAddr":"대구광역시 군위군 부계면 동산리 산76-1","openHours":"상시","maleToilets":2,"femaleToilets":1,"disabled":false,"diaperTable":false,"emergencyBell":false,"cctv":false,"managerTel":"0543806742","source":"public","category":"public"}]