[{"id":"202450200000101296","name":"고현주유소 화장실","lat":36.161599,"lng":129.344031,"roadAddr":"경상북도 포항시 북구 청하면 동해대로 2151","openHours":"상시","maleToilets":4,"femaleToilets":2,"disabled":false,"diaperTable":false,"emergencyBell":false,"cctv":false,"managerTel":"0542320101","source":"public","category":"public"},{"id":"202450200000101297","name":"곡강 주유소 공중화장실","lat":36.128034,"lng":129.347138,"roadAddr":"경상북도 포항시 북구 흥해읍 동해대로 1758","openHours":"상시","maleToilets":2,"femaleToilets":1,"disabled":false,"diaperTable":false,"emergencyBell":false,"cctv":false,"managerTel":"0542407573","source":"public","category":"public"},{"id":"202450200000101369","name":"북포항주유소 화장실","lat":36.15913,"lng":129.345917,"roadAddr":"경상북도 포항시 북구 청하면 동해대로 2123","openHours":"상시","maleToilets":4,"femaleToilets":2,"disabled":false,"diaperTable":false,"emergencyBell":false,"cctv":true,"managerTel":"0542442251","source":"public","category":"public"},{"id":"202250400000100013","name":"용천리 곡강천","lat":36.123924,"lng":129.349922,"jibunAddr":"경상북도 포항시 북구 흥해읍 용천리 1317-1","openHours":"00:00~23:59","maleToilets":3,"femaleToilets":1,"disabled":false,"diaperTable":false,"emergencyBell":false,"cctv":false,"managerTel":"0542407573","source":"public","category":"public"}]