[{"id":"202451800000100160","name":"창수면사무소 화장실","lat":36.546456,"lng":129.348351,"roadAddr":"경상북도 영덕군 창수면 신기길 5","openHours":"정시","maleToilets":4,"femaleToilets":2,"disabled":false,"diaperTable":true,"emergencyBell":false,"cctv":false,"managerTel":"0547307904","source":"public","category":"public"},{"id":"202451800000100150","name":"신기1리 노인게이트볼장","lat":36.545641,"lng":129.349682,"jibunAddr":"경상북도 영덕군 창수면 신기리 56-7","openHours":"상시","maleToilets":1,"femaleToilets":1,"disabled":false,"diaperTable":false,"emergencyBell":false,"cctv":false,"managerTel":"0547307904","source":"public","category":"public"}]