[{"id":"202444600000100065","name":"사리면사무소 화장실","lat":36.816943,"lng":127.64872,"roadAddr":"충청북도 괴산군 사리면 사리로 242","openHours":"09:00~18:00","maleToilets":2,"femaleToilets":2,"disabled":true,"diaperTable":true,"emergencyBell":true,"cctv":false,"managerTel":"0438302585","source":"public","category":"public"},{"id":"202444600000100078","name":"사리보건지소","lat":36.813103,"lng":127.651601,"roadAddr":"충청북도 괴산군 사리면 모래재로 355","openHours":"09:00~18:00","maleToilets":3,"femaleToilets":1,"disabled":false,"diaperTable":false,"emergencyBell":false,"cctv":false,"managerTel":"0438302851","source":"public","category":"public"},{"id":"202555700000100048","name":"신화주유소","lat":36.812639,"lng":127.631986,"roadAddr":"충청북도 증평군 도안면 모래재로 176","jibunAddr":"충청북도 증평군 도안면 도당리 303-7","openHours":"상시","maleToilets":2,"femaleToilets":1,"disabled":false,"diaperTable":false,"emergencyBell":false,"cctv":false,"managerTel":"0438367778","source":"public","category":"public"}]