[{"id":"202435300000101235","name":"논현셀프주유소","lat":37.411318,"lng":126.738346,"roadAddr":"인천광역시 남동구 소래로 233 (논현동)","jibunAddr":"인천광역시 남동구 논현동 33-102","openHours":"상시","maleToilets":3,"femaleToilets":2,"disabled":false,"diaperTable":false,"emergencyBell":false,"cctv":false,"managerTel":"0324536124","source":"public","category":"public"},{"id":"202535300000100004","name":"서창어울마당","lat":37.427217,"lng":126.747449,"roadAddr":"인천광역시 남동구 서창남로 99 (서창동)","jibunAddr":"인천광역시 남동구 서창동 680","openHours":"정시","maleToilets":9,"femaleToilets":13,"disabled":true,"diaperTable":false,"emergencyBell":true,"cctv":false,"managerTel":"0324600573","source":"public","category":"public"},{"id":"202535300000100005","name":"서창배수지체육광장","lat":37.430665,"lng":126.754073,"roadAddr":"인천광역시 남동구 서창남순환로62번길 80 (서창동)","jibunAddr":"인천광역시 남동구 서창동 656","openHours":"상시","maleToilets":3,"femaleToilets":2,"disabled":true,"diaperTable":false,"emergencyBell":true,"cctv":false,"managerTel":"0324536280","source":"public","category":"public"},{"id":"202435300000101114","name":"서창도서관","lat":37.436351,"lng":126.746225,"roadAddr":"인천광역시 남동구 독곡로16번길 15","jibunAddr":"인천광역시 남동구 서창동 558번지 1호","openHours":"정시","maleToilets":11,"femaleToilets":6,"disabled":true,"diaperTable":true,"emergencyBell":true,"cctv":false,"managerTel":"0324535950","source":"public","category":"public"},{"id":"202435300000101187","name":"서창2동 행정복지센터","lat":37.427918,"lng":126.750706,"roadAddr":"인천광역시 남동구 서창남순환로 43","jibunAddr":"인천광역시 남동구 서창동 683","openHours":"정시","maleToilets":13,"femaleToilets":11,"disabled":true,"diaperTable":false,"emergencyBell":true,"cctv":false,"managerTel":"0324535170","source":"public","category":"public"},{"id":"202435300000101137","name":"소래새우","lat":37.400258,"lng":126.740265,"roadAddr":"인천광역시 남동구 소래로 109, 소래새우 공중화장실 (논현동)","jibunAddr":"인천광역시 남동구 논현동 111-244 소래새우 공중화장실","openHours":"상시","maleToilets":3,"femaleToilets":4,"disabled":true,"diaperTable":true,"emergencyBell":true,"cctv":true,"managerTel":"0324532342","source":"public","category":"public"},{"id":"202435300000101084","name":"물빛근린공원","lat":37.421503,"lng":126.747291,"roadAddr":"인천광역시 남동구 서창방산로 22","jibunAddr":"인천광역시 남동구 서창동 713번지","openHours":"상시","maleToilets":5,"femaleToilets":5,"disabled":true,"diaperTable":true,"emergencyBell":true,"cctv":true,"managerTel":"0324536145","source":"public","category":"public"},{"id":"202435300000101041","name":"소래습지생태공원 전시관 화장실","lat":37.407365,"lng":126.746337,"roadAddr":"인천광역시 남동구 소래로154번길 77","jibunAddr":"인천광역시 남동구 논현동 1-1 외 23필지","openHours":"상시","maleToilets":7,"femaleToilets":6,"disabled":true,"diaperTable":true,"emergencyBell":true,"cctv":true,"managerTel":"0324405872","source":"public","category":"public"},{"id":"202435300000101077","name":"서창근린공원","lat":37.436351,"lng":126.746225,"roadAddr":"인천광역시 남동구 독곡로16번길 15, 서창도서관 (서창동)","jibunAddr":"인천광역시 남동구 서창동 558-1 서창도서관","openHours":"상시","maleToilets":6,"femaleToilets":8,"disabled":true,"diaperTable":true,"emergencyBell":true,"cctv":true,"managerTel":"0324536145","source":"public","category":"public"},{"id":"202435300000101015","name":"인천서창동우체국","lat":37.422826,"lng":126.75196,"roadAddr":"인천광역시 남동구 서창방산로 67","jibunAddr":"인천광역시 남동구 서창동 671","openHours":"정시","maleToilets":2,"femaleToilets":1,"disabled":true,"diaperTable":false,"emergencyBell":true,"cctv":false,"managerTel":"0327198311","source":"public","category":"public"},{"id":"202435300000101253","name":"운연역","lat":37.439637,"lng":126.759804,"roadAddr":"인천광역시 남동구 매소홀로 1229","jibunAddr":"인천광역시 남동구 운연동 130-1","openHours":"정시","maleToilets":5,"femaleToilets":5,"disabled":true,"diaperTable":true,"emergencyBell":true,"cctv":true,"managerTel":"0324514327","source":"public","category":"public"},{"id":"202435300000101322","name":"서창지구대","lat":37.435566,"lng":126.747597,"roadAddr":"인천광역시 남동구 독곡로 30","jibunAddr":"인천광역시 남동구 서창동 541","openHours":"상시","maleToilets":2,"femaleToilets":1,"disabled":true,"diaperTable":false,"emergencyBell":false,"cctv":false,"managerTel":"0324549302","source":"public","category":"public"},{"id":"202435300000101237","name":"삼미상사㈜서창셀프주유소","lat":37.428146,"lng":126.760395,"roadAddr":"인천광역시 남동구 서창방산로 165","jibunAddr":"인천광역시 남동구 서창동 741","openHours":"상시","maleToilets":2,"femaleToilets":2,"disabled":false,"diaperTable":false,"emergencyBell":false,"cctv":false,"managerTel":"0324536124","source":"public","category":"public"},{"id":"202435300000101240","name":"장수서창동 행정복지센터","lat":37.435882,"lng":126.747366,"roadAddr":"인천광역시 남동구 독곡로 28","jibunAddr":"인천광역시 남동구 서창동 558-2","openHours":"정시","maleToilets":8,"femaleToilets":7,"disabled":true,"diaperTable":false,"emergencyBell":true,"cctv":true,"managerTel":"0324535500","source":"public","category":"public"},{"id":"202435300000101040","name":"소래습지생태공원 주차장 화장실","lat":37.402751,"lng":126.743854,"roadAddr":"인천광역시 남동구 소래로154번길 78","jibunAddr":"인천광역시 남동구 논현동 66-85","openHours":"상시","maleToilets":5,"femaleToilets":2,"disabled":true,"diaperTable":false,"emergencyBell":true,"cctv":true,"managerTel":"0324405872","source":"public","category":"public"},{"id":"202435300000101083","name":"어울근린공원","lat":37.427502,"lng":126.746107,"roadAddr":"인천광역시 남동구 서창남로 101","jibunAddr":"인천광역시 남동구 서창동 681번지","openHours":"상시","maleToilets":8,"femaleToilets":10,"disabled":true,"diaperTable":true,"emergencyBell":true,"cctv":true,"managerTel":"0324536145","source":"public","category":"public"},{"id":"202435300000101242","name":"투엠프라자","lat":37.426287,"lng":126.748049,"roadAddr":"인천광역시 남동구 서창남로 81","jibunAddr":"인천광역시 남동구 서창동 686-2","openHours":"상시","maleToilets":56,"femaleToilets":24,"disabled":true,"diaperTable":true,"emergencyBell":false,"cctv":true,"source":"public","category":"public"},{"id":"202435300000101030","name":"서창다목적체육관","lat":37.434611,"lng":126.750226,"roadAddr":"인천광역시 남동구 장아산로 190번길 22","jibunAddr":"인천광역시 남동구 서창동 563-8","openHours":"정시","maleToilets":4,"femaleToilets":3,"disabled":false,"diaperTable":false,"emergencyBell":true,"cctv":false,"managerTel":"0324536280","source":"public","category":"public"},{"id":"202435300000101236","name":"동일석유㈜행복드림주유소","lat":37.424696,"lng":126.756653,"roadAddr":"인천광역시 남동구 서창방산로 112","jibunAddr":"인천광역시 남동구 서창동 728","openHours":"상시","maleToilets":9,"femaleToilets":2,"disabled":false,"diaperTable":false,"emergencyBell":false,"cctv":false,"managerTel":"0324536124","source":"public","category":"public"},{"id":"202535300000100009","name":"승연프라자","lat":37.423204,"lng":126.748805,"roadAddr":"인천광역시 남동구 서창남순환로216번길 20, 승연프라자 (서창동)","jibunAddr":"인천광역시 남동구 서창동 703-2 승연프라자","openHours":"상시","maleToilets":6,"femaleToilets":3,"disabled":true,"diaperTable":false,"emergencyBell":false,"cctv":false,"source":"public","category":"public"},{"id":"202435300000101325","name":"인천서창초등학교","lat":37.435891,"lng":126.749826,"roadAddr":"인천광역시 남동구 장아산로174번길 8","jibunAddr":"인천광역시 남동구 서창동 560-6","openHours":"미개방","maleToilets":98,"femaleToilets":84,"disabled":true,"diaperTable":false,"emergencyBell":true,"cctv":false,"managerTel":"0324650226","source":"public","category":"public"},{"id":"202435300000101241","name":"센타프라자","lat":37.424151,"lng":126.749475,"roadAddr":"인천광역시 남동구 서창남순환로 222","jibunAddr":"인천광역시 남동구 서창동 707-1","openHours":"상시","maleToilets":48,"femaleToilets":24,"disabled":true,"diaperTable":true,"emergencyBell":false,"cctv":true,"source":"public","category":"public"},{"id":"202435300000101346","name":"장아산공원(관리소화장실)","lat":37.4275,"lng":126.754354,"roadAddr":"인천광역시 남동구 서창남순환로10번길 21","jibunAddr":"인천광역시 남동구 서창동 649","openHours":"상시","maleToilets":6,"femaleToilets":6,"disabled":true,"diaperTable":false,"emergencyBell":true,"cctv":true,"managerTel":"0324405872","source":"public","category":"public"}]