[{"id":"202540500000101842","name":"동백배드민턴장 공중화장실","lat":37.279088,"lng":127.164529,"roadAddr":"경기도 용인시 기흥구 동백7로 125 (동백동)","jibunAddr":"경기도 용인시 기흥구 동백동 589","openHours":"정시","maleToilets":3,"femaleToilets":2,"disabled":false,"diaperTable":false,"emergencyBell":false,"cctv":false,"managerTel":"07077207334","source":"public","category":"public"},{"id":"202540500000102482","name":"마성영업소","lat":37.284912,"lng":127.176383,"roadAddr":"경기도 용인시 처인구 포곡읍 마성로 1","jibunAddr":"경기도 용인시 처인구 마성리 581-7","openHours":"상시","maleToilets":8,"femaleToilets":6,"disabled":false,"diaperTable":false,"emergencyBell":false,"cctv":true,"managerTel":"0548112812","source":"public","category":"public"},{"id":"202540500000102000","name":"중앙프라자 개방화장실","lat":37.281685,"lng":127.160396,"roadAddr":"경기도 용인시 기흥구 동백7로 83","jibunAddr":"경기도 용인시 기흥구 동백동 598-5","openHours":"상시","maleToilets":16,"femaleToilets":9,"disabled":true,"diaperTable":false,"emergencyBell":false,"cctv":false,"managerTel":"0312866612","source":"public","category":"public"},{"id":"202640500000100038","name":"동백삼성타워 개방화장실","lat":37.272215,"lng":127.151005,"roadAddr":"경기도 용인시 기흥구 동백중앙로 213, 삼성타워 (중동)","jibunAddr":"경기도 용인시 기흥구 중동 847 삼성타워","openHours":"상시","maleToilets":4,"femaleToilets":2,"disabled":false,"diaperTable":false,"emergencyBell":false,"cctv":false,"managerTel":"0316939066","source":"public","category":"public"},{"id":"202640500000100036","name":"동백3동 행정복지센터 개방화장실","lat":37.280453,"lng":127.143749,"roadAddr":"경기도 용인시 기흥구 동백죽전대로527번길 99 (중동)","jibunAddr":"경기도 용인시 기흥구 중동 1106","openHours":"정시","maleToilets":16,"femaleToilets":16,"disabled":true,"diaperTable":false,"emergencyBell":true,"cctv":true,"managerTel":"03161936217","source":"public","category":"public"},{"id":"202540500000102014","name":"동백동다목적구장 공중화장실","lat":37.27346,"lng":127.151381,"roadAddr":"경기도 용인시 기흥구 동백중앙로 214-1 (중동)","jibunAddr":"경기도 용인시 기흥구 중동 866","openHours":"정시","maleToilets":2,"femaleToilets":2,"disabled":true,"diaperTable":false,"emergencyBell":false,"cctv":false,"managerTel":"03161936051","source":"public","category":"public"},{"id":"202540500000102065","name":"석성산 등산로 공중화장실","lat":37.267095,"lng":127.173307,"roadAddr":"경기도 용인시 처인구 동백1로 71-95 (유방동)","jibunAddr":"경기도 용인시 처인구 유방동 산 91-3","openHours":"상시","maleToilets":0,"femaleToilets":1,"disabled":true,"diaperTable":false,"emergencyBell":true,"cctv":false,"managerTel":"07047661315","source":"public","category":"public"},{"id":"202540500000102145","name":"동백호수공원(이마트) 공중화장실","lat":37.276704,"lng":127.150849,"roadAddr":"경기도 용인시 기흥구 동백5로 12","jibunAddr":"경기도 용인시 기흥구 중동 843","openHours":"상시","maleToilets":6,"femaleToilets":5,"disabled":true,"diaperTable":true,"emergencyBell":true,"cctv":true,"managerTel":"03161939053","source":"public","category":"public"},{"id":"202540500000102177","name":"동백도서관 개방화장실","lat":37.274146,"lng":127.158049,"roadAddr":"경기도 용인시 기흥구 동백3로 80 (중동, 동백도서관)","jibunAddr":"경기도 용인시 기흥구 중동 921","openHours":"정시","maleToilets":12,"femaleToilets":20,"disabled":true,"diaperTable":true,"emergencyBell":false,"cctv":true,"managerTel":"03161931318","source":"public","category":"public"},{"id":"202540500000102480","name":"용인(강릉)졸음쉼터","lat":37.288277,"lng":127.139395,"roadAddr":"경기도 용인시 기흥구 영동고속도로 46 (청덕동)","jibunAddr":"경기도 용인시 기흥구 청덕동 422-10","openHours":"상시","maleToilets":3,"femaleToilets":4,"disabled":true,"diaperTable":true,"emergencyBell":true,"cctv":true,"managerTel":"0220841362","source":"public","category":"public"},{"id":"202540500000102116","name":"뜨락문화공원 공중화장실","lat":37.290504,"lng":127.145018,"roadAddr":"경기도 용인시 기흥구 구성로 325 (청덕동)","jibunAddr":"경기도 용인시 기흥구 청덕동 550","openHours":"상시","maleToilets":3,"femaleToilets":2,"disabled":true,"diaperTable":true,"emergencyBell":true,"cctv":true,"managerTel":"03161939081","source":"public","category":"public"},{"id":"202540500000101946","name":"상하동 행정복지센터 개방화장실","lat":37.270513,"lng":127.138397,"roadAddr":"경기도 용인시 기흥구 어정로 62-23, 상하동행정복지센터 (상하동)","jibunAddr":"경기도 용인시 기흥구 상하동 435-12 상하동행정복지센터","openHours":"정시","maleToilets":15,"femaleToilets":12,"disabled":true,"diaperTable":true,"emergencyBell":false,"cctv":true,"managerTel":"03161936782","source":"public","category":"public"},{"id":"202540500000102101","name":"아람근린공원 공중화장실","lat":37.295208,"lng":127.154472,"roadAddr":"경기도 용인시 기흥구 구성로 449 (청덕동)","jibunAddr":"경기도 용인시 기흥구 청덕동 564","openHours":"상시","maleToilets":5,"femaleToilets":5,"disabled":true,"diaperTable":false,"emergencyBell":true,"cctv":true,"managerTel":"03161939081","source":"public","category":"public"},{"id":"202540500000102204","name":"용인경전철 어정역 개방화장실","lat":37.274959,"lng":127.143856,"roadAddr":"경기도 용인시 기흥구 어정로 128, 어정역 (상하동)","jibunAddr":"경기도 용인시 기흥구 상하동 620-50 어정역","openHours":"정시","maleToilets":4,"femaleToilets":5,"disabled":true,"diaperTable":true,"emergencyBell":true,"cctv":true,"managerTel":"0313293544","source":"public","category":"public"},{"id":"202540500000101903","name":"용인동부경찰서 동백지구대 개방화장실","lat":37.27755,"lng":127.155474,"roadAddr":"경기도 용인시 기흥구 동백6로 37, 동백파출소 (중동)","jibunAddr":"경기도 용인시 기흥구 중동 872-2 동백파출소","openHours":"상시","maleToilets":4,"femaleToilets":2,"disabled":true,"diaperTable":true,"emergencyBell":false,"cctv":true,"managerTel":"0312600480","source":"public","category":"public"},{"id":"202540500000102012","name":"동백산오름공원테니스장 공중화장실","lat":37.278846,"lng":127.164943,"roadAddr":"경기도 용인시 기흥구 동백7로 129 (동백동)","jibunAddr":"경기도 용인시 기흥구 동백동 589","openHours":"정시","maleToilets":6,"femaleToilets":3,"disabled":false,"diaperTable":false,"emergencyBell":false,"cctv":false,"managerTel":"03161936051","source":"public","category":"public"},{"id":"202540500000102138","name":"새물근린공원 공중화장실","lat":37.280395,"lng":127.15546,"roadAddr":"경기도 용인시 기흥구 동백평촌로 63 (동백동)","jibunAddr":"경기도 용인시 기흥구 동백동 657","openHours":"상시","maleToilets":3,"femaleToilets":2,"disabled":true,"diaperTable":true,"emergencyBell":true,"cctv":true,"managerTel":"03161939053","source":"public","category":"public"},{"id":"202540500000102220","name":"용인시박물관 공중화장실","lat":37.273925,"lng":127.157158,"roadAddr":"경기도 용인시 기흥구 동백3로 79 (중동)","jibunAddr":"경기도 용인시 기흥구 중동 862","openHours":"정시","maleToilets":9,"femaleToilets":5,"disabled":true,"diaperTable":true,"emergencyBell":true,"cctv":true,"managerTel":"03161934795","source":"public","category":"public"},{"id":"202540500000101927","name":"용인동백우체국 개방화장실","lat":37.277371,"lng":127.155633,"roadAddr":"경기도 용인시 기흥구 동백6로 39, 용인동백우체국 (중동)","jibunAddr":"경기도 용인시 기흥구 중동 872-3 용인동백우체국","openHours":"정시","maleToilets":0,"femaleToilets":0,"disabled":true,"diaperTable":false,"emergencyBell":false,"cctv":true,"managerTel":"0316939848","source":"public","category":"public"},{"id":"202540500000101884","name":"동백119안전센터 개방화장실","lat":37.277724,"lng":127.155213,"roadAddr":"경기도 용인시 기흥구 동백6로 33, 용인소방서 동백119 (중동)","jibunAddr":"경기도 용인시 기흥구 중동 872-1 용인소방서 동백119","openHours":"상시","maleToilets":12,"femaleToilets":3,"disabled":false,"diaperTable":false,"emergencyBell":false,"cctv":false,"managerTel":"03161903551","source":"public","category":"public"},{"id":"202640500000100023","name":"동백호수공원(광장) 공중화장실","lat":37.274771,"lng":127.149766,"roadAddr":"경기도 용인시 기흥구 동백중앙로 235 (중동)","jibunAddr":"경기도 용인시 기흥구 중동 843","openHours":"상시","maleToilets":4,"femaleToilets":3,"disabled":true,"diaperTable":true,"emergencyBell":true,"cctv":true,"managerTel":"03161939053","source":"public","category":"public"},{"id":"202640500000100024","name":"푸르내어린이공원 공중화장실","lat":37.282781,"lng":127.163296,"roadAddr":"경기도 용인시 기흥구 동백8로 120 (동백동)","jibunAddr":"경기도 용인시 기흥구 동백동 594","openHours":"상시","maleToilets":6,"femaleToilets":4,"disabled":true,"diaperTable":true,"emergencyBell":true,"cctv":true,"source":"public","category":"public"},{"id":"202540500000102210","name":"용인경전철 동백역 개방화장실","lat":37.269151,"lng":127.15276,"roadAddr":"경기도 용인시 기흥구 동백죽전대로 314, 동백역 (중동)","jibunAddr":"경기도 용인시 기흥구 중동 1087 동백역","openHours":"정시","maleToilets":4,"femaleToilets":5,"disabled":true,"diaperTable":true,"emergencyBell":true,"cctv":true,"managerTel":"0313293545","source":"public","category":"public"},{"id":"202540500000101947","name":"동백2동 행정복지센터 개방화장실","lat":37.272533,"lng":127.151687,"roadAddr":"경기도 용인시 기흥구 동백중앙로 214","jibunAddr":"경기도 용인시 기흥구 866-1","openHours":"정시","maleToilets":12,"femaleToilets":10,"disabled":true,"diaperTable":true,"emergencyBell":true,"cctv":true,"managerTel":"03161936742","source":"public","category":"public"},{"id":"202540500000102201","name":"용인경전철 지석역 개방화장실","lat":37.269768,"lng":127.136642,"roadAddr":"경기도 용인시 기흥구 어정로 28, 지석역 (상하동)","jibunAddr":"경기도 용인시 기흥구 상하동 401-1 지석역","openHours":"정시","maleToilets":3,"femaleToilets":4,"disabled":true,"diaperTable":true,"emergencyBell":true,"cctv":true,"managerTel":"0313293543","source":"public","category":"public"},{"id":"202540500000102163","name":"청덕도서관 개방화장실","lat":37.292798,"lng":127.14743,"roadAddr":"경기도 용인시 기흥구 구성1로 44","jibunAddr":"경기도 용인시 기흥구 청덕동 549","openHours":"정시","maleToilets":9,"femaleToilets":6,"disabled":true,"diaperTable":true,"emergencyBell":true,"cctv":true,"managerTel":"03161931350","source":"public","category":"public"},{"id":"202640500000100010","name":"미래도프라자 개방화장실","lat":37.281577,"lng":127.160879,"roadAddr":"경기도 용인시 기흥구 동백중앙로 358-19, 미래도프라자 (동백동)","jibunAddr":"경기도 용인시 기흥구 동백동 597-1 미래도프라자","openHours":"상시","maleToilets":4,"femaleToilets":2,"disabled":false,"diaperTable":false,"emergencyBell":false,"cctv":false,"source":"public","category":"public"},{"id":"202258050000100037","name":"광주고려요양병원","lat":37.290387,"lng":127.138404,"roadAddr":"구성로 268 (계림동)","openHours":"09:00~18:00","maleToilets":6,"femaleToilets":2,"disabled":true,"diaperTable":false,"emergencyBell":false,"cctv":false,"source":"public","category":"public"}]