[{"id":"202543510000100084","name":"해당화충전소 화장실","lat":37.984438,"lng":128.750876,"roadAddr":"강원특별자치도 양양군 현남면 동해대로 964","openHours":"정시","maleToilets":3,"femaleToilets":1,"disabled":false,"diaperTable":false,"emergencyBell":false,"cctv":false,"source":"public","category":"public"},{"id":"202543510000100089","name":"38휴게소","lat":38.004125,"lng":128.732723,"roadAddr":"강원특별자치도 양양군 현북면 잔교리 41-10","openHours":"정시","maleToilets":10,"femaleToilets":8,"disabled":true,"diaperTable":true,"emergencyBell":false,"cctv":false,"source":"public","category":"public"},{"id":"202543510000100022","name":"잔교리 화장실1","lat":37.992477,"lng":128.743064,"roadAddr":"강원특별자치도 양양군 현북면 동해대로 1080","openHours":"정시","maleToilets":4,"femaleToilets":1,"disabled":false,"diaperTable":false,"emergencyBell":false,"cctv":false,"source":"public","category":"public"},{"id":"202543510000100023","name":"잔교리 화장실2","lat":37.992477,"lng":128.743064,"roadAddr":"강원특별자치도 양양군 현북면 동해대로 1080","openHours":"정시","maleToilets":10,"femaleToilets":8,"disabled":false,"diaperTable":false,"emergencyBell":false,"cctv":false,"source":"public","category":"public"},{"id":"202543510000100136","name":"동산리 해수욕장 화장실","lat":37.978046,"lng":128.75944,"jibunAddr":"강원특별자치도 양양군 현남면 동산리 90-35","openHours":"정시","maleToilets":4,"femaleToilets":4,"disabled":false,"diaperTable":false,"emergencyBell":true,"cctv":false,"source":"public","category":"public"},{"id":"202543510000100166","name":"동산해수욕장 야영장 화장실","lat":37.981752,"lng":128.756447,"jibunAddr":"강원특별자치도 양양군 현남면 동산리 203-54","openHours":"정시","maleToilets":2,"femaleToilets":3,"disabled":true,"diaperTable":true,"emergencyBell":true,"cctv":false,"source":"public","category":"public"},{"id":"202543510000100138","name":"기사문항(등대) 화장실","lat":38.005601,"lng":128.730838,"roadAddr":"강원특별자치도 양양군 현북면 기사문길 8","jibunAddr":"강원특별자치도 양양군 현북면 기사문리 89-37","openHours":"정시","maleToilets":5,"femaleToilets":3,"disabled":true,"diaperTable":true,"emergencyBell":true,"cctv":false,"source":"public","category":"public"},{"id":"202543510000100139","name":"기사문항 화장실","lat":38.008789,"lng":128.730703,"roadAddr":"강원특별자치도 양양군 현북면 기사문길 42","jibunAddr":"강원특별자치도 양양군 현북면 기사문리 89-32","openHours":"정시","maleToilets":5,"femaleToilets":2,"disabled":false,"diaperTable":false,"emergencyBell":true,"cctv":false,"source":"public","category":"public"},{"id":"202543510000100017","name":"현남면사무소 화장실","lat":37.96924,"lng":128.759474,"roadAddr":"강원특별자치도 양양군 현남면 인구중앙길 45","openHours":"정시","maleToilets":4,"femaleToilets":2,"disabled":true,"diaperTable":false,"emergencyBell":false,"cctv":false,"source":"public","category":"public"},{"id":"202543510000100135","name":"해양레포츠센터 화장실","lat":37.975003,"lng":128.759083,"jibunAddr":"강원특별자치도 양양군 현남면 시변리 산1-1","openHours":"정시","maleToilets":5,"femaleToilets":5,"disabled":true,"diaperTable":false,"emergencyBell":true,"cctv":false,"source":"public","category":"public"}]